.DS_Store
shared_dataverse_information/__init__.py
shared_dataverse_information/dataverse_info/__init__.py
shared_dataverse_information/dataverse_info/admin.py
shared_dataverse_information/dataverse_info/forms.py
shared_dataverse_information/dataverse_info/forms_existing_layer.py
shared_dataverse_information/dataverse_info/models.py
shared_dataverse_information/dataverse_info/testrunner.py
shared_dataverse_information/dataverse_info/url_helper.py
shared_dataverse_information/layer_classification/__init__.py
shared_dataverse_information/layer_classification/admin.py
shared_dataverse_information/layer_classification/api_url_helper.py
shared_dataverse_information/layer_classification/classify_format_helper.py
shared_dataverse_information/layer_classification/forms.py
shared_dataverse_information/layer_classification/forms_api.py
shared_dataverse_information/layer_classification/models.py
shared_dataverse_information/layer_classification/fixtures/initial_data.json
shared_dataverse_information/map_layer_metadata/__init__.py
shared_dataverse_information/map_layer_metadata/form_helper.py
shared_dataverse_information/map_layer_metadata/forms.py
shared_dataverse_information/map_layer_metadata/models.py
shared_dataverse_information/shapefile_import/__init__.py
shared_dataverse_information/shapefile_import/forms.py
shared_dataverse_information/shapefile_import/models.py
shared_dataverse_information/shared_form_util/__init__.py
shared_dataverse_information/shared_form_util/format_form_errors.py
shared_dataverse_information/shared_form_util/version_help.py
shared_dataverse_information/worldmap_api_helper/__init__.py
shared_dataverse_information/worldmap_api_helper/forms_api_validate.py
shared_dataverse_information/worldmap_api_helper/url_helper.py
shared_dataverse_information/worldmap_datatables/__init__.py
shared_dataverse_information/worldmap_datatables/delimiter_helper.py
shared_dataverse_information/worldmap_datatables/forms.py
shared_dataverse_information-0.5.7.dist-info/DESCRIPTION.rst
shared_dataverse_information-0.5.7.dist-info/METADATA
shared_dataverse_information-0.5.7.dist-info/metadata.json
shared_dataverse_information-0.5.7.dist-info/pbr.json
shared_dataverse_information-0.5.7.dist-info/RECORD
shared_dataverse_information-0.5.7.dist-info/top_level.txt
shared_dataverse_information-0.5.7.dist-info/WHEEL
