Metadata-Version: 2.0
Name: shared-dataverse-information
Version: 0.5.7
Summary: Shared code for the Dataverse and WorldMap connection.
Home-page: https://github.com/IQSS/shared-dataverse-information
Author: R Prasad
Author-email: raman_prasad@harvard.edu
License: MIT
Keywords: sample setuptools development
Platform: UNKNOWN
Classifier: Development Status :: 2 - Pre-Alpha
Classifier: Intended Audience :: Developers
Classifier: License :: OSI Approved :: MIT License
Classifier: Programming Language :: Python :: 2.6
Classifier: Programming Language :: Python :: 2.7
Requires-Dist: Django (>=1.4,<1.7)
Requires-Dist: requests (==2.3.0)
